LICENSE.txt
MANIFEST.in
README.md
VERSION
pyproject.toml
requirements.txt
setup.cfg
setup.py
deon/__init__.py
deon/__main__.py
deon/cli.py
deon/deon.py
deon/formats.py
deon/parser.py
deon.egg-info/PKG-INFO
deon.egg-info/SOURCES.txt
deon.egg-info/dependency_links.txt
deon.egg-info/entry_points.txt
deon.egg-info/requires.txt
deon.egg-info/top_level.txt
deon/assets/checklist.yml
deon/assets/examples_of_ethical_issues.yml