Metadata-Version: 2.1
Name: deon
Version: 0.3.0
Summary: Deon adds an ethics checklist to your data science projects.
Home-page: http://deon.drivendata.org
Author: DrivenData
Author-email: info@drivendata.org
License: MIT
Project-URL: Homepage, http://deon.drivendata.org
Project-URL: Source Code, https://github.com/drivendataorg/deon
Project-URL: DrivenData, http://drivendata.co
Keywords: data science,ethics,checklist
Platform: UNKNOWN
Classifier: Programming Language :: Python
Classifier: Programming Language :: Python :: 3
Classifier: Programming Language :: Python :: 3.6
Classifier: Intended Audience :: Developers
Classifier: Intended Audience :: Science/Research
Classifier: License :: OSI Approved :: MIT License
Classifier: Topic :: Scientific/Engineering
Classifier: Topic :: Scientific/Engineering :: Artificial Intelligence
Requires-Python: >=3.6
